[
    {
        "key": "group_5ce31d377ad2d",
        "title": "Home",
        "fields": [
            {
                "key": "field_5ce3211845baa",
                "label": "Título Banner",
                "name": "titulo_banner",
                "type": "text",
                "instructions": "",
                "required": 1,
                "conditional_logic": 0,
                "wrapper": {
                    "width": "",
                    "class": "",
                    "id": ""
                },
                "default_value": "",
                "placeholder": "",
                "prepend": "",
                "append": "",
                "maxlength": ""
            },
            {
                "key": "field_5ce3212845bab",
                "label": "Texto Banner",
                "name": "texto_banner",
                "type": "wysiwyg",
                "instructions": "",
                "required": 1,
                "conditional_logic": 0,
                "wrapper": {
                    "width": "",
                    "class": "",
                    "id": ""
                },
                "default_value": "",
                "tabs": "visual",
                "toolbar": "basic",
                "media_upload": 0,
                "delay": 0
            },
            {
                "key": "field_5ce31d44003b7",
                "label": "Testimonios",
                "name": "testimonios",
                "type": "repeater",
                "instructions": "",
                "required": 0,
                "conditional_logic": 0,
                "wrapper": {
                    "width": "",
                    "class": "",
                    "id": ""
                },
                "collapsed": "",
                "min": 0,
                "max": 0,
                "layout": "table",
                "button_label": "",
                "sub_fields": [
                    {
                        "key": "field_5ce31db2003b8",
                        "label": "Nombre",
                        "name": "nombre",
                        "type": "text",
                        "instructions": "",
                        "required": 1,
                        "conditional_logic": 0,
                        "wrapper": {
                            "width": "",
                            "class": "",
                            "id": ""
                        },
                        "default_value": "",
                        "placeholder": "",
                        "prepend": "",
                        "append": "",
                        "maxlength": ""
                    },
                    {
                        "key": "field_5ce31dc1003b9",
                        "label": "Imagen",
                        "name": "imagen",
                        "type": "image",
                        "instructions": "",
                        "required": 1,
                        "conditional_logic": 0,
                        "wrapper": {
                            "width": "",
                            "class": "",
                            "id": ""
                        },
                        "return_format": "array",
                        "preview_size": "thumbnail",
                        "library": "all",
                        "min_width": "",
                        "min_height": "",
                        "min_size": "",
                        "max_width": "",
                        "max_height": "",
                        "max_size": "",
                        "mime_types": ""
                    },
                    {
                        "key": "field_5ce31e0d003ba",
                        "label": "Testimonio",
                        "name": "testimonio",
                        "type": "textarea",
                        "instructions": "",
                        "required": 1,
                        "conditional_logic": 0,
                        "wrapper": {
                            "width": "",
                            "class": "",
                            "id": ""
                        },
                        "default_value": "",
                        "placeholder": "",
                        "maxlength": "",
                        "rows": "",
                        "new_lines": ""
                    }
                ]
            }
        ],
        "location": [
            [
                {
                    "param": "page",
                    "operator": "==",
                    "value": "7"
                }
            ]
        ],
        "menu_order": 0,
        "position": "normal",
        "style": "default",
        "label_placement": "top",
        "instruction_placement": "label",
        "hide_on_screen": "",
        "active": true,
        "description": ""
    }
]